[
  {
    "name": "fox.jason.passthrough.swagger",
    "description": "DITA-OT Plug-in to automatically create REST API documentation from a Swagger definition",
    "keywords": [
      "swagger",
      "REST",
      "auto-generated text"
    ],
    "homepage": "https://jason-fox.github.io/fox.jason.passthrough.swagger",
    "vers": "1.0.0",
    "license": "Apache-2.0",
    "deps": [
      {
        "name": "org.dita.base",
        "req": ">=3.0.0"
      },
      {
        "name": "org.doctales.xmltask",
        "req": ">=1.16.1"
      },
      {
        "name": "fox.jason.passthrough",
        "req": ">=1.0.0"
      },
      {
        "name": "fox.jason.passthrough.pandoc",
        "req": ">=1.1.0"
      }
    ],
    "url": "https://github.com/jason-fox/fox.jason.passthrough.swagger/archive/v1.0.0.zip",
    "cksum": "22177754825c75f835077e434845ff608c5d4b88e10cc65cc01ed3ca168d7d9f"
  },
  {
    "name": "fox.jason.passthrough.swagger",
    "description": "DITA-OT Plug-in to automatically create REST API documentation from a Swagger definition",
    "keywords": [
      "swagger",
      "REST",
      "auto-generated text"
    ],
    "homepage": "https://jason-fox.github.io/fox.jason.passthrough.swagger",
    "vers": "1.1.0",
    "license": "Apache-2.0",
    "deps": [
      {
        "name": "org.dita.base",
        "req": ">=3.0.0"
      },
      {
        "name": "org.doctales.xmltask",
        "req": ">=1.16.1"
      },
      {
        "name": "fox.jason.extend.css",
        "req": ">=1.0.0"
      },
      {
        "name": "fox.jason.passthrough",
        "req": ">=2.1.0"
      },
      {
        "name": "fox.jason.passthrough.pandoc",
        "req": ">=1.2.0"
      }
    ],
    "url": "https://github.com/jason-fox/fox.jason.passthrough.swagger/archive/v1.1.0.zip",
    "cksum": "88e8f17bf37526f80330e7155a94a7fc2f2c6bdd6d6837e90d27833d6ddea8ec"
  },
  {
    "name": "fox.jason.passthrough.swagger",
    "description": "DITA-OT Plug-in to automatically create REST API documentation from a Swagger definition",
    "keywords": [
      "swagger",
      "REST",
      "auto-generated text"
    ],
    "homepage": "https://jason-fox.github.io/fox.jason.passthrough.swagger",
    "vers": "1.1.1",
    "license": "Apache-2.0",
    "deps": [
      {
        "name": "org.dita.base",
        "req": ">=3.0.0"
      },
      {
        "name": "org.doctales.xmltask",
        "req": ">=1.16.1"
      },
      {
        "name": "fox.jason.extend.css",
        "req": ">=1.0.0"
      },
      {
        "name": "fox.jason.passthrough",
        "req": ">=2.2.0"
      },
      {
        "name": "fox.jason.passthrough.pandoc",
        "req": ">=1.2.1"
      }
    ],
    "url": "https://github.com/jason-fox/fox.jason.passthrough.swagger/archive/v1.1.1.zip",
    "cksum": "2b3b36961a4db9c79447dd1e2059ba4f2e03990ad63875fe43d53e522e0f2488"
  },
  {
    "name": "fox.jason.passthrough.swagger",
    "description": "DITA-OT Plug-in to automatically create REST API documentation from a Swagger definition",
    "keywords": [
      "swagger",
      "REST",
      "auto-generated text"
    ],
    "homepage": "https://jason-fox.github.io/fox.jason.passthrough.swagger",
    "vers": "1.2.0",
    "license": "Apache-2.0",
    "deps": [
      {
        "name": "org.dita.base",
        "req": ">=3.0.0"
      },
      {
        "name": "org.doctales.xmltask",
        "req": ">=1.16.1"
      },
      {
        "name": "fox.jason.extend.css",
        "req": ">=1.0.1"
      },
      {
        "name": "fox.jason.passthrough",
        "req": ">=3.0.0"
      },
      {
        "name": "fox.jason.passthrough.pandoc",
        "req": ">=1.3.0"
      }
    ],
    "url": "https://github.com/jason-fox/fox.jason.passthrough.swagger/archive/v1.2.0.zip",
    "cksum": "7daa42f6ae909b2b1a675f37a678e6693015d3d382e96a01bc9082e9262e46cc"
  },
  {
    "name": "fox.jason.passthrough.swagger",
    "description": "DITA-OT Plug-in to automatically create REST API documentation from a Swagger definition",
    "keywords": [
      "swagger",
      "REST",
      "auto-generated text"
    ],
    "homepage": "https://jason-fox.github.io/fox.jason.passthrough.swagger",
    "vers": "1.3.0",
    "license": "Apache-2.0",
    "deps": [
      {
        "name": "org.dita.base",
        "req": ">=3.0.0"
      },
      {
        "name": "org.doctales.xmltask",
        "req": ">=1.16.1"
      },
      {
        "name": "fox.jason.extend.css",
        "req": ">=1.0.1"
      },
      {
        "name": "fox.jason.passthrough",
        "req": ">=3.1.0"
      },
      {
        "name": "fox.jason.passthrough.pandoc",
        "req": ">=1.3.0"
      }
    ],
    "url": "https://github.com/jason-fox/fox.jason.passthrough.swagger/archive/v1.3.0.zip",
    "cksum": "dcc8d99f2f3fe9585feccb1da4e6269e6782e097f4694ff2805a91fdd1f1cf33"
  },
  {
    "name": "fox.jason.passthrough.swagger",
    "description": "DITA-OT Plug-in to automatically create REST API documentation from a Swagger definition",
    "keywords": [
      "swagger",
      "REST",
      "auto-generated text"
    ],
    "homepage": "https://jason-fox.github.io/fox.jason.passthrough.swagger",
    "vers": "2.0.0",
    "license": "Apache-2.0",
    "deps": [
      {
        "name": "org.dita.base",
        "req": ">=3.0.0"
      },
      {
        "name": "fox.jason.extend.css",
        "req": ">=1.0.3"
      },
      {
        "name": "fox.jason.passthrough",
        "req": ">=4.0.0"
      },
      {
        "name": "fox.jason.passthrough.pandoc",
        "req": ">=2.0.0"
      }
    ],
    "url": "https://github.com/jason-fox/fox.jason.passthrough.swagger/archive/v2.0.0.zip",
    "cksum": "a1a0b390107f8d5f5bd952ee916deeb2996f8bb990515d20dbe700238e991600"
  },
  {
    "name": "fox.jason.passthrough.swagger",
    "description": "DITA-OT Plug-in to automatically create REST API documentation from a Swagger definition",
    "keywords": [
      "swagger",
      "REST",
      "auto-generated text"
    ],
    "homepage": "https://jason-fox.github.io/fox.jason.passthrough.swagger",
    "vers": "2.0.1",
    "license": "Apache-2.0",
    "deps": [
      {
        "name": "org.dita.base",
        "req": ">=3.0.0"
      },
      {
        "name": "fox.jason.extend.css",
        "req": ">=1.0.3"
      },
      {
        "name": "fox.jason.passthrough",
        "req": ">=4.0.0"
      },
      {
        "name": "fox.jason.passthrough.pandoc",
        "req": ">=2.0.0"
      }
    ],
    "url": "https://github.com/jason-fox/fox.jason.passthrough.swagger/archive/v2.0.1.zip",
    "cksum": "d2ed32be087204a2a9dd2c94611284641b7208c83b07bf4892e9d2e008ce5ec8"
  }
]
